README.md
setup.py
sumtype/__init__.py
sumtype/sumtype.py
sumtype/sumtype_meta.py
sumtype/sumtype_slots.py
sumtype.egg-info/PKG-INFO
sumtype.egg-info/SOURCES.txt
sumtype.egg-info/dependency_links.txt
sumtype.egg-info/requires.txt
sumtype.egg-info/top_level.txt
sumtype/experimental/__init__.py
sumtype/experimental/pattern_matching.py
sumtype/experimental/sumtype_plain_tuple.py
sumtype/tests/__init__.py
sumtype/tests/preview_output.py
sumtype/tests/profile.py
sumtype/tests/property_tests.py
sumtype/tests/test_functionality.py
sumtype/tests/test_readme.py