Metadata-Version: 2.1
Name: sumtype
Version: 0.10.0.post3
Summary: A namedtuple-style library for defining immutable sum types in Python.
Home-page: UNKNOWN
Author: J Uryga
Author-email: lolzatu2@gmail.com
License: UNKNOWN
Project-URL: Source, https://github.com/lubieowoce/sumtype
Keywords: sum variant tagged union enum type types
Platform: UNKNOWN
Requires-Python: >=3
